{"cameraMode":{"drawMode":0,"name":"Shaded","section":"Shading Mode"},"sceneLighting":true,"audioPlay":false,"sceneViewState":{"m_AlwaysRefresh":false,"showFog":true,"showSkybox":true,"showFlares":true,"showImageEffects":true,"showParticleSystems":true,"showVisualEffectGraphs":true,"m_FxEnabled":true},"in2DMode":false,"pivot":{"x":-58.90892028808594,"y":2.036365509033203,"z":-4.601287841796875},"rotation":{"x":0.357429563999176,"y":0.06109397113323212,"z":-0.02332478016614914,"w":0.9317036867141724},"size":39.862396240234378,"orthographic":false}